{
  "maxSpend": {
    "maxSpend": {
      "amount": "2243", 
      "date": "24/12/2019", 
      "type": "rent"
    }
  }, 
  "maximum": "2243", 
  "mean": "363.8888888888889", 
  "median": "189.0", 
  "minSpend": {
    "minSpend": {
      "amount": "7", 
      "date": "02/07/2019", 
      "type": "food"
    }
  }, 
  "minimum": "7", 
  "monthBased": {
    "amount": {
      "1": 213, 
      "10": 552, 
      "11": 155, 
      "12": 2550, 
      "3": 454, 
      "4": 43, 
      "5": 1586, 
      "6": 134, 
      "7": 517, 
      "8": 13, 
      "9": 333
    }
  }, 
  "monthlyYear": {
    "amount": {
      "1-2019": 213, 
      "10-2019": 552, 
      "11-2019": 155, 
      "12-2019": 2550, 
      "3-2019": 454, 
      "4-2019": 43, 
      "5-2019": 1586, 
      "6-2019": 134, 
      "7-2019": 517, 
      "8-2019": 13, 
      "9-2019": 333
    }
  }, 
  "sum": "6550", 
  "targetPerc": {
    "target": {
      "": "", 
      "coffee": "2", 
      "food": "20", 
      "gas": "8", 
      "phone bill": "7", 
      "rent": "30"
    }
  }, 
  "typeBased": {
    "amount": {
      "food": 3405, 
      "gas": 422, 
      "phone bill": 480, 
      "rent": 2243
    }, 
    "percentage": {
      "food": 22.7, 
      "gas": 2.8133333333333335, 
      "phone bill": 3.2, 
      "rent": 14.953333333333333
    }
  }, 
  "year": "2019"
}
